setup.py
distr_probability/Binomialdistribution.py
distr_probability/Gaussiandistribution.py
distr_probability/Generaldistribution.py
distr_probability/__init__.py
distr_probability.egg-info/PKG-INFO
distr_probability.egg-info/SOURCES.txt
distr_probability.egg-info/dependency_links.txt
distr_probability.egg-info/not-zip-safe
distr_probability.egg-info/top_level.txt