Metadata-Version: 1.0
Name: distr-probability
Version: 0.1
Summary: Gaussian & Binomial distributions
Home-page: UNKNOWN
Author: Adhi Wibowo
Author-email: UNKNOWN
License: UNKNOWN
Platform: UNKNOWN
